xai_agg/__init__.py
xai_agg/agg_exp.py
xai_agg/exp_utils.py
xai_agg/explainers.py
xai_agg/mp.py
xai_agg/tools.py
xai_agg-0.1.0.dist-info/METADATA
xai_agg-0.1.0.dist-info/WHEEL
xai_agg-0.1.0.dist-info/top_level.txt
xai_agg-0.1.0.dist-info/RECORD
