Metadata-Version: 2.4
Name: xai-agg
Version: 0.1.0
Summary: Rank based, multi-criteria aggregation method for explainable AI models.
Home-page: https://github.com/hiaac-finance/xai_aggregation
Author: Everton Colombo
Author-email: everton.colombo@students.ic.unicamp.br
Project-URL: Source Code, https://github.com/hiaac-finance/xai_aggregation
Project-URL: Documentation, https://xai-agg.readthedocs.io/en/latest/
Requires-Python: >=3.10
Requires-Dist: scikit-learn
Requires-Dist: numpy
Requires-Dist: pandas
Requires-Dist: lime
Requires-Dist: shap
Requires-Dist: alibi
Requires-Dist: scipy
Requires-Dist: tensorflow-cpu
Requires-Dist: tf-keras
Requires-Dist: pathos
Requires-Dist: pymcdm
Requires-Dist: ranx
Requires-Dist: xlrd
Requires-Dist: pandera
Requires-Dist: ipython
Dynamic: author
Dynamic: author-email
Dynamic: description
Dynamic: description-content-type
Dynamic: home-page
Dynamic: project-url
Dynamic: requires-dist
Dynamic: requires-python
Dynamic: summary
